CHANGES.rst
CONTRIBUTORS.rst
DEVELOP.rst
LICENSE.GPL
LICENSE.rst
MANIFEST.in
README.rst
setup.cfg
setup.py
docs/conf.py
docs/index.rst
src/collective/__init__.py
src/collective.accordionviews.egg-info/PKG-INFO
src/collective.accordionviews.egg-info/SOURCES.txt
src/collective.accordionviews.egg-info/dependency_links.txt
src/collective.accordionviews.egg-info/entry_points.txt
src/collective.accordionviews.egg-info/namespace_packages.txt
src/collective.accordionviews.egg-info/not-zip-safe
src/collective.accordionviews.egg-info/requires.txt
src/collective.accordionviews.egg-info/top_level.txt
src/collective/accordionviews/__init__.py
src/collective/accordionviews/configure.zcml
src/collective/accordionviews/interfaces.py
src/collective/accordionviews/permissions.zcml
src/collective/accordionviews/setuphandlers.py
src/collective/accordionviews/testing.py
src/collective/accordionviews/browser/__init__.py
src/collective/accordionviews/browser/configure.zcml
src/collective/accordionviews/browser/overrides/.gitkeep
src/collective/accordionviews/browser/static/.gitkeep
src/collective/accordionviews/browser/static/main.css
src/collective/accordionviews/locales/README.rst
src/collective/accordionviews/locales/__init__.py
src/collective/accordionviews/locales/collective.accordionviews.pot
src/collective/accordionviews/locales/manual.pot
src/collective/accordionviews/locales/update.py
src/collective/accordionviews/locales/de/LC_MESSAGES/collective.accordionviews.po
src/collective/accordionviews/locales/en/LC_MESSAGES/collective.accordionviews.po
src/collective/accordionviews/profiles/default/browserlayer.xml
src/collective/accordionviews/profiles/default/catalog.xml
src/collective/accordionviews/profiles/default/metadata.xml
src/collective/accordionviews/profiles/default/rolemap.xml
src/collective/accordionviews/profiles/default/types.xml
src/collective/accordionviews/profiles/default/registry/main.xml
src/collective/accordionviews/profiles/default/types/Collection.xml
src/collective/accordionviews/profiles/default/types/Folder.xml
src/collective/accordionviews/profiles/uninstall/browserlayer.xml
src/collective/accordionviews/tests/__init__.py
src/collective/accordionviews/tests/test_robot.py
src/collective/accordionviews/tests/test_setup.py
src/collective/accordionviews/tests/test_upgrade_step_1001.py
src/collective/accordionviews/tests/test_upgrade_step_1002.py
